cryptoconfig/__init__.py
cryptoconfig/core.py
cryptoconfig/encryptor.py
cryptoconfig/formats/__init__.py
cryptoconfig/formats/ini_handler.py
cryptoconfig/formats/json_handler.py
cryptoconfig/formats/properties_handler.py
cryptoconfig/formats/txt_handler.py
cryptoconfig/formats/yaml_handler.py
tests/__init__.py
tests/test_core.py
tests/test_encryptor.py
tests/test_ini_handler.py
tests/test_json_handler.py
tests/test_properties_handler.py
tests/test_txt_handler.py
tests/test_with_config_files.py
tests/test_yaml_handler.py
configlock-0.1.2.dist-info/LICENSE.md
configlock-0.1.2.dist-info/METADATA
configlock-0.1.2.dist-info/WHEEL
configlock-0.1.2.dist-info/top_level.txt
configlock-0.1.2.dist-info/RECORD
