Metadata-Version: 2.1
Name: configlock
Version: 0.1.2
Summary: Encrypted configuration manager supporting multiple formats.
Home-page: https://github.com/felicedev/encryptedconfig
Author: FeliceDev
Author-email: felicedev@outlook.com
Classifier: Programming Language :: Python :: 3
Classifier: License :: OSI Approved :: MIT License
Classifier: Operating System :: OS Independent
Requires-Python: >=3.6
License-File: LICENSE.md
Requires-Dist: cryptography
Requires-Dist: PyYAML
